{
  "meta": {
    "login_detected": false,
    "found": true
  },
  "entries": [
    {
      "distance_label": "3,1 mi",
      "distance_mi": 3.1,
      "required_pct": 7,
      "weekly": "ca. 5 mi",
      "long_run": "-",
      "achieved_pct": 1500,
      "achieved_ok": true,
      "prognosis_time": "22:27",
      "optimum_time": null
    },
    {
      "distance_label": "6,2 mi",
      "distance_mi": 6.2,
      "required_pct": 17,
      "weekly": "ca. 11 mi",
      "long_run": "-",
      "achieved_pct": 639,
      "achieved_ok": true,
      "prognosis_time": "46:34",
      "optimum_time": null
    },
    {
      "distance_label": "10,0 mi",
      "distance_mi": 10.0,
      "required_pct": 31,
      "weekly": "ca. 20 mi",
      "long_run": "-",
      "achieved_pct": 356,
      "achieved_ok": true,
      "prognosis_time": "1:17:19",
      "optimum_time": null
    },
    {
      "distance_label": "13,1 mi",
      "distance_mi": 13.1,
      "required_pct": 43,
      "weekly": "ca. 26 mi",
      "long_run": "ca. 12 mi",
      "achieved_pct": 255,
      "achieved_ok": true,
      "prognosis_time": "1:43:14",
      "optimum_time": null
    },
    {
      "distance_label": "26,2 mi",
      "distance_mi": 26.2,
      "required_pct": 100,
      "weekly": "ca. 45 mi",
      "long_run": "ca. 18 mi",
      "achieved_pct": 109,
      "achieved_ok": true,
      "prognosis_time": "3:34:18",
      "optimum_time": null
    },
    {
      "distance_label": "31,1 mi",
      "distance_mi": 31.1,
      "required_pct": 123,
      "weekly": "ca. 48 mi",
      "long_run": "ca. 20 mi",
      "achieved_pct": 88,
      "achieved_ok": false,
      "prognosis_time": "4:27:52",
      "optimum_time": "4:15:11"
    },
    {
      "distance_label": "62,1 mi",
      "distance_mi": 62.1,
      "required_pct": 288,
      "weekly": "ca. 65 mi",
      "long_run": "ca. 31 mi",
      "achieved_pct": 38,
      "achieved_ok": false,
      "prognosis_time": "12:48:45",
      "optimum_time": "8:33:52"
    },
    {
      "distance_label": "100,0 mi",
      "distance_mi": 100.0,
      "required_pct": 518,
      "weekly": "ca. 116 mi",
      "long_run": "ca. 39 mi",
      "achieved_pct": 21,
      "achieved_ok": false,
      "prognosis_time": "20:36:55",
      "optimum_time": "13:47:08"
    }
  ],
  "_meta": {
    "last_updated": "2025-12-21T01:59:50Z"
  }
}